CHANGELOG.txt
LICENSE.txt
MANIFEST.in
README.txt
setup.py
ishopatoz-text-extract/__init__.py
ishopatoz-text-extract/textextract.py
ishopatoz_text_extract.egg-info/PKG-INFO
ishopatoz_text_extract.egg-info/SOURCES.txt
ishopatoz_text_extract.egg-info/dependency_links.txt
ishopatoz_text_extract.egg-info/top_level.txt
textextract.egg-info/SOURCES.txt
textextract.egg-info/dependency_links.txt
textextract.egg-info/top_level.txt
venv/Lib/site-packages/_virtualenv.py
venv/Lib/site-packages/easy_install.py
venv/Lib/site-packages/six.py
venv/Lib/site-packages/Jinja2-3.1.3.dist-info/entry_points.txt
venv/Lib/site-packages/Jinja2-3.1.3.dist-info/top_level.txt
venv/Lib/site-packages/MarkupSafe-2.1.5.dist-info/top_level.txt
venv/Lib/site-packages/blinker/__init__.py
venv/Lib/site-packages/blinker/_saferef.py
venv/Lib/site-packages/blinker/_utilities.py
venv/Lib/site-packages/blinker/base.py
venv/Lib/site-packages/certifi/__init__.py
venv/Lib/site-packages/certifi/__main__.py
venv/Lib/site-packages/certifi/core.py
venv/Lib/site-packages/certifi-2024.2.2.dist-info/top_level.txt
venv/Lib/site-packages/chardet/__init__.py
venv/Lib/site-packages/chardet/big5freq.py
venv/Lib/site-packages/chardet/big5prober.py
venv/Lib/site-packages/chardet/chardistribution.py
venv/Lib/site-packages/chardet/charsetgroupprober.py
venv/Lib/site-packages/chardet/charsetprober.py
venv/Lib/site-packages/chardet/codingstatemachine.py
venv/Lib/site-packages/chardet/compat.py
venv/Lib/site-packages/chardet/cp949prober.py
venv/Lib/site-packages/chardet/enums.py
venv/Lib/site-packages/chardet/escprober.py
venv/Lib/site-packages/chardet/escsm.py
venv/Lib/site-packages/chardet/eucjpprober.py
venv/Lib/site-packages/chardet/euckrfreq.py
venv/Lib/site-packages/chardet/euckrprober.py
venv/Lib/site-packages/chardet/euctwfreq.py
venv/Lib/site-packages/chardet/euctwprober.py
venv/Lib/site-packages/chardet/gb2312freq.py
venv/Lib/site-packages/chardet/gb2312prober.py
venv/Lib/site-packages/chardet/hebrewprober.py
venv/Lib/site-packages/chardet/jisfreq.py
venv/Lib/site-packages/chardet/jpcntx.py
venv/Lib/site-packages/chardet/langbulgarianmodel.py
venv/Lib/site-packages/chardet/langcyrillicmodel.py
venv/Lib/site-packages/chardet/langgreekmodel.py
venv/Lib/site-packages/chardet/langhebrewmodel.py
venv/Lib/site-packages/chardet/langhungarianmodel.py
venv/Lib/site-packages/chardet/langthaimodel.py
venv/Lib/site-packages/chardet/langturkishmodel.py
venv/Lib/site-packages/chardet/latin1prober.py
venv/Lib/site-packages/chardet/mbcharsetprober.py
venv/Lib/site-packages/chardet-3.0.4.dist-info/entry_points.txt
venv/Lib/site-packages/chardet-3.0.4.dist-info/top_level.txt
venv/Lib/site-packages/charset_normalizer-3.3.2.dist-info/entry_points.txt
venv/Lib/site-packages/charset_normalizer-3.3.2.dist-info/top_level.txt
venv/Lib/site-packages/click-8.1.7.dist-info/top_level.txt
venv/Lib/site-packages/colorama-0.4.6.dist-info/licenses/LICENSE.txt
venv/Lib/site-packages/flask-3.0.2.dist-info/entry_points.txt
venv/Lib/site-packages/fpdf-1.7.2.dist-info/top_level.txt
venv/Lib/site-packages/googletrans-3.0.0.dist-info/top_level.txt
venv/Lib/site-packages/h11-0.9.0.dist-info/LICENSE.txt
venv/Lib/site-packages/h11-0.9.0.dist-info/top_level.txt
venv/Lib/site-packages/h2-3.2.0.dist-info/top_level.txt
venv/Lib/site-packages/hpack-3.0.0.dist-info/top_level.txt
venv/Lib/site-packages/hstspreload-2024.2.1.dist-info/top_level.txt
venv/Lib/site-packages/httpcore-0.9.1.dist-info/top_level.txt
venv/Lib/site-packages/httpx-0.13.3.dist-info/top_level.txt
venv/Lib/site-packages/hyperframe-5.2.0.dist-info/top_level.txt
venv/Lib/site-packages/idna-2.8.dist-info/top_level.txt
venv/Lib/site-packages/itsdangerous-2.1.2.dist-info/top_level.txt
venv/Lib/site-packages/nanonets-2.0.5.dist-info/top_level.txt
venv/Lib/site-packages/numpy-1.24.4.dist-info/LICENSE.txt
venv/Lib/site-packages/numpy-1.24.4.dist-info/LICENSES_bundled.txt
venv/Lib/site-packages/numpy-1.24.4.dist-info/entry_points.txt
venv/Lib/site-packages/numpy-1.24.4.dist-info/top_level.txt
venv/Lib/site-packages/ocr_nanonets_wrapper-1.1.dist-info/top_level.txt
venv/Lib/site-packages/pandas-2.0.3.dist-info/entry_points.txt
venv/Lib/site-packages/pandas-2.0.3.dist-info/top_level.txt
venv/Lib/site-packages/pip-21.3.1.dist-info/LICENSE.txt
venv/Lib/site-packages/pip-21.3.1.dist-info/entry_points.txt
venv/Lib/site-packages/pip-21.3.1.dist-info/top_level.txt
venv/Lib/site-packages/python_dateutil-2.8.2.dist-info/top_level.txt
venv/Lib/site-packages/pytz-2024.1.dist-info/LICENSE.txt
venv/Lib/site-packages/pytz-2024.1.dist-info/top_level.txt
venv/Lib/site-packages/requests-2.22.0.dist-info/top_level.txt
venv/Lib/site-packages/rfc3986-1.5.0.dist-info/top_level.txt
venv/Lib/site-packages/setuptools-41.0.1.dist-info/dependency_links.txt
venv/Lib/site-packages/setuptools-41.0.1.dist-info/entry_points.txt
venv/Lib/site-packages/setuptools-41.0.1.dist-info/top_level.txt
venv/Lib/site-packages/six-1.16.0.dist-info/top_level.txt
venv/Lib/site-packages/sniffio-1.3.0.dist-info/top_level.txt
venv/Lib/site-packages/tqdm-4.36.1.dist-info/entry_points.txt
venv/Lib/site-packages/tqdm-4.36.1.dist-info/top_level.txt
venv/Lib/site-packages/tzdata-2023.4.dist-info/top_level.txt
venv/Lib/site-packages/urllib3-1.25.11.dist-info/LICENSE.txt
venv/Lib/site-packages/urllib3-1.25.11.dist-info/top_level.txt
venv/Lib/site-packages/wheel-0.37.1.dist-info/LICENSE.txt
venv/Lib/site-packages/wheel-0.37.1.dist-info/entry_points.txt
venv/Lib/site-packages/wheel-0.37.1.dist-info/top_level.txt
venv/Lib/site-packages/xmljson-0.2.0.dist-info/LICENSE.txt
venv/Lib/site-packages/xmljson-0.2.0.dist-info/entry_points.txt
venv/Lib/site-packages/xmljson-0.2.0.dist-info/top_level.txt
