Metadata-Version: 1.0
Name: ishopatoz-text-extract
Version: 1.1
Summary: My first Python library
Home-page: UNKNOWN
Author: Me
Author-email: UNKNOWN
License: UNKNOWN
Platform: UNKNOWN
